quick_ollama/__init__.py
quick_ollama/__main__.py
quick_ollama/main.py
quick_ollama-0.0.7.dist-info/METADATA
quick_ollama-0.0.7.dist-info/WHEEL
quick_ollama-0.0.7.dist-info/top_level.txt
quick_ollama-0.0.7.dist-info/RECORD
